README.rst
setup.py
pyopen/__init__.py
pyopen/command.py
pyopen/load.py
pyopen/temp_files.py
pyopen/web.py
pyopen.egg-info/PKG-INFO
pyopen.egg-info/SOURCES.txt
pyopen.egg-info/dependency_links.txt
pyopen.egg-info/entry_points.txt
pyopen.egg-info/requires.txt
pyopen.egg-info/top_level.txt
pyopen/loaders/__init__.py
pyopen/loaders/base.py
pyopen/loaders/json.py
pyopen/loaders/pandas_csv.py
pyopen/loaders/pandas_hdf5.py
pyopen/loaders/pandas_xls.py
pyopen/loaders/pickle.py
pyopen/loaders/text.py
pyopen/loaders/yaml.py
test/test_basics.py