Metadata-Version: 1.1
Name: pyopen
Version: 0.0.7
Summary: launch an interactive ipython session with specified files opened and parsed
Home-page: https://github.com/timodonnell/pyopen
Author: Tim O'Donnell
Author-email: timodonnell@gmail.com
License: Apache License
Download-URL: https://github.com/timodonnell/pyopen/tarball/0.0.7
Platform: UNKNOWN
Classifier: Development Status :: 1 - Planning
Classifier: Intended Audience :: Developers
Classifier: Programming Language :: Python :: 2
Classifier: Programming Language :: Python :: 2.7
Classifier: Programming Language :: Python :: 3
Classifier: Programming Language :: Python :: 3.4
